LICENSE
MANIFEST.in
README.md
setup.py
setup_nogui.py
bin/jamstats
bin/jamstats-nogui
resources/cumulative_score_by_jam.png
resources/current_skaters.png
resources/jam_points_barplot.png
resources/jammer_stats.png
resources/jammer_summary.png
resources/jamstats_icon.ico
resources/jamstats_icon.png
resources/jamstats_logo.png
resources/jamstats_socialmedia.png
resources/jamstats_version.txt
resources/lead_summary.png
resources/sdb_logo_whitebkgrnd.png
resources/skater_stats.png
resources/team_penalty_counts.png
resources/tsv_output_screenshot.png
src/build/jamstats/xref-jamstats.html
src/jamstats/__init__.py
src/jamstats.egg-info/PKG-INFO
src/jamstats.egg-info/SOURCES.txt
src/jamstats.egg-info/dependency_links.txt
src/jamstats.egg-info/requires.txt
src/jamstats.egg-info/top_level.txt
src/jamstats/data/__init__.py
src/jamstats/data/game_data.py
src/jamstats/data/json_to_pandas.py
src/jamstats/io/__init__.py
src/jamstats/io/scoreboard_json_io.py
src/jamstats/io/scoreboard_server_io.py
src/jamstats/io/tsv_io.py
src/jamstats/plots/__init__.py
src/jamstats/plots/advanced_plots.py
src/jamstats/plots/basic_plots.py
src/jamstats/plots/plot_together.py
src/jamstats/plots/plot_util.py
src/jamstats/resources/__init__.py
src/jamstats/resources/jamstats_logo.png
src/jamstats/resources/jamstats_version.txt
src/jamstats/static/jamstats_icon.ico
src/jamstats/static/sdb_logo.png
src/jamstats/static/styles/normalize.css
src/jamstats/static/styles/skeleton.css
src/jamstats/tables/__init__.py
src/jamstats/tables/jamstats_tables.py
src/jamstats/tables/table_util.py
src/jamstats/templates/jamstats_gameplots.html
src/jamstats/util/__init__.py
src/jamstats/util/resources.py
src/jamstats/web/__init__.py
src/jamstats/web/statserver.py
webapp/static/jamstats_icon.ico
webapp/static/sdb_logo.png
webapp/static/styles/normalize.css
webapp/static/styles/skeleton.css
webapp/templates/display_game_plots.html
webapp/templates/upload_game.html