Metadata-Version: 2.1
Name: jamstats
Version: 3.5.1
Summary: Data processing, stats and plots on roller derby scoreboard JSON files
Author: Damon May
Project-URL: Source, https://github.com/dhmay/jamstats
Classifier: Development Status :: 3 - Alpha
Classifier: Programming Language :: Python :: 3
Classifier: Programming Language :: Python :: 3.7
License-File: LICENSE
Requires-Dist: pandas>=2.2.0
Requires-Dist: seaborn>=0.13.2
Requires-Dist: flask>=3.0.2
Requires-Dist: eventlet>=0.35.1
Requires-Dist: websocket-client>=1.7.0
Requires-Dist: Flask-SocketIO>=5.3.6
Requires-Dist: python-engineio>=4.9.0
Requires-Dist: gevent>=24.2.1
Requires-Dist: gevent-websocket>=0.10.1
Requires-Dist: dnspython==2.2.1
Requires-Dist: urllib3==1.26.7
Requires-Dist: wxpython>=4.2.1
Requires-Dist: gooey>=1.0.8.1
